pysatl/__init__.py
pysatl/core/__init__.py
pysatl/core/expon.py
pysatl/core/weibull.py
pysatl/criterion/__init__.py
pysatl/criterion/common.py
pysatl/criterion/exponent.py
pysatl/criterion/goodness_of_fit.py
pysatl/criterion/graph_goodness_of_fit.py
pysatl/criterion/models.py
pysatl/criterion/normal.py
pysatl/criterion/weibull.py
pysatl_criterion-0.0.1a0.dist-info/LICENSE
pysatl_criterion-0.0.1a0.dist-info/METADATA
pysatl_criterion-0.0.1a0.dist-info/WHEEL
pysatl_criterion-0.0.1a0.dist-info/RECORD
