Metadata-Version: 2.3
Name: pysatl-criterion
Version: 0.0.1a0
Summary: Package with statistic criteria for PySATL
License: MIT
Author: PySATL Team
Author-email: pysatl@yahoo.com
Requires-Python: >=3.9,<3.13
Classifier: License :: OSI Approved :: MIT License
Classifier: Programming Language :: Python :: 3
Classifier: Programming Language :: Python :: 3.9
Classifier: Programming Language :: Python :: 3.10
Classifier: Programming Language :: Python :: 3.11
Classifier: Programming Language :: Python :: 3.12
Requires-Dist: numpy (>=1.25.1)
Requires-Dist: pandas (>=2.2.1)
Requires-Dist: scipy (>=1.11.2)
Requires-Dist: typing-extensions (>=4.12.2)
Project-URL: Homepage, https://github.com/PySATL/pysatl-criterion
Project-URL: Issues, https://github.com/PySATL/pysatl-criterion/issues
